[
{"symbol": "KIE", "name": "SPDR S&P Insurance ETF", "price": 51.1, "change": 0.45, "change_rate": 0.9, "volume": "165,594", "fifty_day_average": 48.6, "hundred_day_average": 44.34, "previous_close": 49.5, "open": 49.5},
{"symbol": "GXG", "name": "Global X MSCI Colombia ETF", "price": 24.73, "change": 0.2, "change_rate": 0.82, "volume": "3,903", "fifty_day_average": 23.45, "hundred_day_average": 21.93, "previous_close": 23.29, "open": 23.44},
{"symbol": "EZA", "name": "iShares MSCI South Africa ETF", "price": 38.55, "change": 0.32, "change_rate": 0.84, "volume": "16,354", "fifty_day_average": 38.48, "hundred_day_average": 39.5, "previous_close": 37.74, "open": 38.69},
{"symbol": "OMFS", "name": "Invesco Russell 2000 Dynamic Multifactor ETF", "price": 36.89, "change": 0.39, "change_rate": 1.07, "volume": "3,516", "fifty_day_average": 36.53, "hundred_day_average": 35.81, "previous_close": 36.43, "open": 36.86},
{"symbol": "PTF", "name": "Invesco Dorsey Wright Technology Momentum ETF", "price": 57.92, "change": 0.49, "change_rate": 0.85, "volume": "1,964", "fifty_day_average": 53.5, "hundred_day_average": 48.56, "previous_close": 54.49, "open": 55.61},
{"symbol": "PICK", "name": "iShares MSCI Global Metals & Mining Producers ETF", "price": 41.42, "change": 0.34, "change_rate": 0.83, "volume": "68,828", "fifty_day_average": 40.01, "hundred_day_average": 40.27, "previous_close": 39.34, "open": 39.51},
{"symbol": "FTXN", "name": "First Trust Nasdaq Oil & Gas ETF", "price": 32.0, "change": 0.35, "change_rate": 1.12, "volume": "8,025", "fifty_day_average": 28.89, "hundred_day_average": 28.64, "previous_close": 29.23, "open": 29.14},
{"symbol": "PDBC", "name": "Invesco Optimum Yield Diversified Commodity Strategy No K-1 ETF", "price": 13.88, "change": 0.15, "change_rate": 1.13, "volume": "578,961", "fifty_day_average": 13.42, "hundred_day_average": 14.11, "previous_close": 13.13, "open": 13.16},
{"symbol": "DBC", "name": "Invesco DB Commodity Index Tracking Fund", "price": 22.98, "change": 0.27, "change_rate": 1.17, "volume": "411,804", "fifty_day_average": 22.22, "hundred_day_average": 23.49, "previous_close": 21.74, "open": 21.81},
{"symbol": "PXE", "name": "Invesco Dynamic Energy Exploration & Production ETF", "price": 35.37, "change": 0.41, "change_rate": 1.17, "volume": "10,624", "fifty_day_average": 31.57, "hundred_day_average": 31.0, "previous_close": 32.69, "open": 32.78},
{"symbol": "VDE", "name": "Vanguard Energy Index Fund ETF Shares", "price": 130.49, "change": 1.59, "change_rate": 1.23, "volume": "138,039", "fifty_day_average": 119.42, "hundred_day_average": 119.76, "previous_close": 124.16, "open": 124.28},
{"symbol": "IYE", "name": "iShares U.S. Energy ETF", "price": 48.86, "change": 0.59, "change_rate": 1.22, "volume": "137,348", "fifty_day_average": 44.79, "hundred_day_average": 45.0, "previous_close": 45.15, "open": 45.07},
{"symbol": "SLX", "name": "VanEck Steel ETF", "price": 71.84, "change": 0.72, "change_rate": 1.01, "volume": "2,806", "fifty_day_average": 69.81, "hundred_day_average": 67.32, "previous_close": 70.18, "open": 70.14},
{"symbol": "IEO", "name": "iShares U.S. Oil & Gas Exploration & Production ETF", "price": 105.58, "change": 1.34, "change_rate": 1.29, "volume": "26,483", "fifty_day_average": 94.73, "hundred_day_average": 93.8, "previous_close": 94.84, "open": 95.05},
{"symbol": "FENY", "name": "Fidelity MSCI Energy Index ETF", "price": 25.65, "change": 0.34, "change_rate": 1.34, "volume": "161,001", "fifty_day_average": 23.45, "hundred_day_average": 23.51, "previous_close": 23.64, "open": 23.63},
{"symbol": "IDX", "name": "VanEck Indonesia Index ETF", "price": 16.49, "change": 0.25, "change_rate": 1.54, "volume": "1,626", "fifty_day_average": 16.34, "hundred_day_average": 17.25, "previous_close": 16.05, "open": 16.32},
{"symbol": "GOAU", "name": "U.S. Global GO GOLD and Precious Metal Miners ETF", "price": 17.01, "change": 0.28, "change_rate": 1.7, "volume": "4,563", "fifty_day_average": 15.77, "hundred_day_average": 16.1, "previous_close": 15.89, "open": 16.24},
{"symbol": "BLOK", "name": "Amplify Transformational Data Sharing ETF", "price": 36.05, "change": 1.17, "change_rate": 3.35, "volume": "74,802", "fifty_day_average": 30.85, "hundred_day_average": 25.15, "previous_close": 34.47, "open": 34.63},
{"symbol": "XLE", "name": "Energy Select Sector SPDR Fund", "price": 93.53, "change": 1.13, "change_rate": 1.22, "volume": "5.082M", "fifty_day_average": 85.58, "hundred_day_average": 85.64, "previous_close": 88.17, "open": 88.19},
{"symbol": "GDX", "name": "VanEck Gold Miners ETF", "price": 30.18, "change": 0.58, "change_rate": 1.95, "volume": "5.693M", "fifty_day_average": 28.06, "hundred_day_average": 29.15, "previous_close": 30.13, "open": 29.55}
]